ssh_metro_server-0.1.5.dist-info/DESCRIPTION.rst
ssh_metro_server-0.1.5.dist-info/METADATA
ssh_metro_server-0.1.5.dist-info/RECORD
ssh_metro_server-0.1.5.dist-info/WHEEL
ssh_metro_server-0.1.5.dist-info/entry_points.txt
ssh_metro_server-0.1.5.dist-info/metadata.json
ssh_metro_server-0.1.5.dist-info/top_level.txt
sshmetroserver/__init__.py
sshmetroserver/main.py
sshmetroserver/model.py
sshmetroserver/util.py
