Metadata-Version: 2.0
Name: ssh-metro-server
Version: 0.1.5
Summary: An SSH tunnel server.
Home-page: https://github.com/thilux/ssh_metro_server
Author: thilux (Thiago Santana)
Author-email: thilux.systems@gmail.com
License: Apache 2
Keywords: python pexpect ssh flask tunnel ssh-tunnel
Platform: UNKNOWN
Classifier: Development Status :: 3 - Alpha
Classifier: Intended Audience :: Developers
Classifier: Intended Audience :: Information Technology
Classifier: Intended Audience :: System Administrators
Classifier: License :: OSI Approved :: Apache Software License
Classifier: Topic :: Software Development :: Build Tools
Classifier: Programming Language :: Python
Classifier: Programming Language :: Python :: 2
Classifier: Programming Language :: Python :: 2.6
Classifier: Programming Language :: Python :: 2.7
Classifier: Programming Language :: Python :: 3
Classifier: Programming Language :: Python :: 3.4
Classifier: Programming Language :: Python :: 3.5
Classifier: Programming Language :: Python :: 3.6
Classifier: Programming Language :: Python :: Implementation :: CPython
Classifier: Programming Language :: Python :: Implementation :: PyPy
Requires-Python: >=2.6, !=3.0.*, !=3.1.*, !=3.2.*, !=3.3.*
Requires-Dist: flask
Requires-Dist: pexpect
Requires-Dist: argparse
Provides-Extra: testing
Requires-Dist: flask; extra == 'testing'
Requires-Dist: pexpect; extra == 'testing'
Requires-Dist: argparse; extra == 'testing'
